procvision_algorithm_sdk/__init__.py
procvision_algorithm_sdk/base.py
procvision_algorithm_sdk/cli.py
procvision_algorithm_sdk/diagnostics.py
procvision_algorithm_sdk/errors.py
procvision_algorithm_sdk/logger.py
procvision_algorithm_sdk/session.py
procvision_algorithm_sdk/shared_memory.py
procvision_algorithm_sdk/adapter/__init__.py
procvision_algorithm_sdk/adapter/__main__.py
procvision_algorithm_sdk-0.3.0.dist-info/METADATA
procvision_algorithm_sdk-0.3.0.dist-info/WHEEL
procvision_algorithm_sdk-0.3.0.dist-info/entry_points.txt
procvision_algorithm_sdk-0.3.0.dist-info/top_level.txt
procvision_algorithm_sdk-0.3.0.dist-info/RECORD
