Metadata-Version: 2.4
Name: procvision-algorithm-sdk
Version: 0.3.0
Summary: ProcVision Algorithm SDK
Author-email: Southwest AI Team <ai@southwest.com>
License: MIT
Requires-Python: >=3.8
Requires-Dist: numpy
